pymlem/__init__.py
pymlem/pymlem.py
pymlem-0.6.dist-info/METADATA
pymlem-0.6.dist-info/WHEEL
pymlem-0.6.dist-info/top_level.txt
pymlem-0.6.dist-info/RECORD
