Metadata-Version: 2.1
Name: pymlem
Version: 0.6
Summary: A brief description of your package
Home-page: UNKNOWN
Author: witchietherichie
Author-email: witchietherichie@hotmal.com
License: UNKNOWN
Platform: UNKNOWN
Classifier: Programming Language :: Python :: 3
Classifier: License :: OSI Approved :: MIT License
Classifier: Operating System :: OS Independent
Requires-Python: >=3.6
